strawberry_sqlalchemy/__init__.py
strawberry_sqlalchemy-0.1.5.dist-info/LICENSE
strawberry_sqlalchemy-0.1.5.dist-info/WHEEL
strawberry_sqlalchemy-0.1.5.dist-info/METADATA
strawberry_sqlalchemy-0.1.5.dist-info/RECORD
