Metadata-Version: 2.1
Name: strawberry_sqlalchemy
Version: 0.1.5
Summary: A helper library to integrate sqlalchemy models with strawberry-graphql
Author-email: Ambro17 <ambro17.1@gmail.com>
Requires-Python: >=3.7
Classifier: License :: OSI Approved :: GNU General Public License v3 or later (GPLv3+)
Requires-Dist: strawberry-graphql>=0.9
Requires-Dist: sqlalchemy>=1
